preprod/__init__.py
preprod/commons.py
preprod/core.py
preprod/locale/en/LC_MESSAGES/preprod.mo
preprod/locale/en.po
preprod/locale/es/LC_MESSAGES/preprod.mo
preprod/locale/es.po
preprod/locale/preprod.pot
preprod/poethepoet.py
preprod/tests/test_commons.py
preprod-1.3.0.dist-info/LICENSE
preprod-1.3.0.dist-info/METADATA
preprod-1.3.0.dist-info/WHEEL
preprod-1.3.0.dist-info/entry_points.txt
preprod-1.3.0.dist-info/RECORD
