Metadata-Version: 2.3
Name: preprod
Version: 1.3.0
Summary: Easily creation of pre-production and production scripts to automete your deployment
License: GPL-3.0-only
Author: turulomio
Author-email: turulomio@yahoo.es
Requires-Python: >=3.11,<4.0.0
Classifier: License :: OSI Approved :: GNU General Public License v3 (GPLv3)
Classifier: Programming Language :: Python :: 3
Classifier: Programming Language :: Python :: 3.11
Classifier: Programming Language :: Python :: 3.12
Classifier: Programming Language :: Python :: 3.13
Requires-Dist: colorama (>=0.4.6,<0.5.0)
Project-URL: Homepage, https://github.com/turulomio/preprod/
Project-URL: Repository, https://github.com/turulomio/preprod/
Project-URL: changelog, https://github.com/turulomio/preprod#changelog
